prodige_core/__init__.py
prodige_core/config.py
prodige_core/data_display.py
prodige_core/data_handler.py
prodige_core/source_catalogue.py
prodige_core/sources.csv
prodige_core/test/__init__.py
prodige_core/test/conftest.py
prodige_core/test/test_data_display.py
prodige_core/test/test_data_handler.py
prodige_core/test/test_source_catalogue.py
prodige_core/test/baseline_images/test_data_display/example_map.png
prodige_core-0.6.dist-info/LICENSE
prodige_core-0.6.dist-info/METADATA
prodige_core-0.6.dist-info/WHEEL
prodige_core-0.6.dist-info/top_level.txt
prodige_core-0.6.dist-info/RECORD
